kotlinwrapper1/__init__.py
kotlinwrapper1/temp.txt
kotlinwrapper1-0.1.3.dist-info/METADATA
kotlinwrapper1-0.1.3.dist-info/WHEEL
kotlinwrapper1-0.1.3.dist-info/top_level.txt
kotlinwrapper1-0.1.3.dist-info/RECORD
