Metadata-Version: 2.4
Name: kotlinwrapper1
Version: 0.1.3
Summary: A test package that includes temp.txt
Author: Your Name
Dynamic: author
Dynamic: summary
